EAGS/EAGS.py
EAGS/EAGS_function.py
EAGS/__init__.py
EAGS-1.0.5.dist-info/LICENSE
EAGS-1.0.5.dist-info/METADATA
EAGS-1.0.5.dist-info/WHEEL
EAGS-1.0.5.dist-info/top_level.txt
EAGS-1.0.5.dist-info/RECORD
